django_migrations_tui/__init__.py
django_migrations_tui/management/__init__.py
django_migrations_tui/management/commands/__init__.py
django_migrations_tui/management/commands/migrationstui.py
django_migrations_tui/tui/__init__.py
django_migrations_tui/tui/app.py
django_migrations_tui/tui/confirmation.py
django_migrations_tui/tui/logs.py
django_migrations_tui/tui/tree.py
django_migrations_tui/tui/utils.py
django_migrations_tui/tui/static/app.tcss
django_migrations_tui-0.1.10.dist-info/LICENSE
django_migrations_tui-0.1.10.dist-info/METADATA
django_migrations_tui-0.1.10.dist-info/WHEEL
django_migrations_tui-0.1.10.dist-info/top_level.txt
django_migrations_tui-0.1.10.dist-info/RECORD
