Metadata-Version: 2.1
Name: django-migrations-tui
Version: 0.1.10
Summary: Manage Django Migrations with a Text-Based UI.
Author-email: Taulant Aliraj <taliraj@outlook.com>
Maintainer-email: Taulant Aliraj <taliraj@outlook.com>
License: MIT License
Project-URL: Homepage, https://github.com/taliraj/django-migrations-tui
Project-URL: Repository, https://github.com/taliraj/django-migrations-tui
Classifier: Environment :: Web Environment
Classifier: Framework :: Django
Classifier: Intended Audience :: Developers
Classifier: Programming Language :: Python :: 3 :: Only
Classifier: Programming Language :: Python :: 3.8
Classifier: Programming Language :: Python :: 3.9
Classifier: Programming Language :: Python :: 3.10
Classifier: Programming Language :: Python :: 3.11
Classifier: Programming Language :: Python :: 3.12
Requires-Python: >=3.8
License-File: LICENSE
Requires-Dist: Django
Requires-Dist: textual >=0.37.0
Provides-Extra: test
Requires-Dist: pytest ; extra == 'test'
Requires-Dist: pytest-asyncio ; extra == 'test'
Requires-Dist: pytest-django ; extra == 'test'
